{
  "sentences_examples": [
    {
      "id": "",
      "sentence_zh": "章鱼很聪明。",
      "sentence_pinyin": "Zhāngyú hěn cōngming.",
      "sentence_fr": "La pieuvre est intelligente.",
      "sentence_en": "The octopus is smart.",
      "audio_url_male": null,
      "difficulty": "initiation",
      "category": "animals",
      "created_at": "2025-11-20T13:35:00.000Z",
      "updated_at": "2025-11-20T13:35:00.000Z"
    },
    {
      "id": "",
      "sentence_zh": "贝壳很漂亮。",
      "sentence_pinyin": "Bèiké hěn piàoliang.",
      "sentence_fr": "Le coquillage est beau.",
      "sentence_en": "The shell is beautiful.",
      "audio_url_male": null,
      "difficulty": "initiation",
      "category": "nature",
      "created_at": "2025-11-20T13:35:00.000Z",
      "updated_at": "2025-11-20T13:35:00.000Z"
    },
    {
      "id": "",
      "sentence_zh": "珍珠很贵。",
      "sentence_pinyin": "Zhēnzhū hěn guì.",
      "sentence_fr": "La perle est chère.",
      "sentence_en": "The pearl is expensive.",
      "audio_url_male": null,
      "difficulty": "initiation",
      "category": "shopping",
      "created_at": "2025-11-20T13:35:00.000Z",
      "updated_at": "2025-11-20T13:35:00.000Z"
    },
    {
      "id": "",
      "sentence_zh": "海鲜很鲜。",
      "sentence_pinyin": "Hǎixiān hěn xiān.",
      "sentence_fr": "Les fruits de mer sont frais.",
      "sentence_en": "The seafood is fresh.",
      "audio_url_male": null,
      "difficulty": "initiation",
      "category": "food",
      "created_at": "2025-11-20T13:35:00.000Z",
      "updated_at": "2025-11-20T13:35:00.000Z"
    },
    {
      "id": "",
      "sentence_zh": "牛肉很嫩。",
      "sentence_pinyin": "Niúròu hěn nèn.",
      "sentence_fr": "Le bœuf est tendre.",
      "sentence_en": "The beef is tender.",
      "audio_url_male": null,
      "difficulty": "initiation",
      "category": "food",
      "created_at": "2025-11-20T13:35:00.000Z",
      "updated_at": "2025-11-20T13:35:00.000Z"
    },
    {
      "id": "",
      "sentence_zh": "羊肉很香。",
      "sentence_pinyin": "Yángròu hěn xiāng.",
      "sentence_fr": "Le mouton sent bon.",
      "sentence_en": "The lamb smells good.",
      "audio_url_male": null,
      "difficulty": "initiation",
      "category": "food",
      "created_at": "2025-11-20T13:35:00.000Z",
      "updated_at": "2025-11-20T13:35:00.000Z"
    },
    {
      "id": "",
      "sentence_zh": "猪肉很便宜。",
      "sentence_pinyin": "Zhūròu hěn piányi.",
      "sentence_fr": "Le porc est bon marché.",
      "sentence_en": "Pork is cheap.",
      "audio_url_male": null,
      "difficulty": "initiation",
      "category": "food",
      "created_at": "2025-11-20T13:35:00.000Z",
      "updated_at": "2025-11-20T13:35:00.000Z"
    },
    {
      "id": "",
      "sentence_zh": "鸡肉很嫩。",
      "sentence_pinyin": "Jīròu hěn nèn.",
      "sentence_fr": "Le poulet est tendre.",
      "sentence_en": "The chicken is tender.",
      "audio_url_male": null,
      "difficulty": "initiation",
      "category": "food",
      "created_at": "2025-11-20T13:35:00.000Z",
      "updated_at": "2025-11-20T13:35:00.000Z"
    },
    {
      "id": "",
      "sentence_zh": "鸭肉很肥。",
      "sentence_pinyin": "Yāròu hěn féi.",
      "sentence_fr": "Le canard est gras.",
      "sentence_en": "The duck is fatty.",
      "audio_url_male": null,
      "difficulty": "initiation",
      "category": "food",
      "created_at": "2025-11-20T13:35:00.000Z",
      "updated_at": "2025-11-20T13:35:00.000Z"
    },
    {
      "id": "",
      "sentence_zh": "火腿很咸。",
      "sentence_pinyin": "Huǒtuǐ hěn xián.",
      "sentence_fr": "Le jambon est salé.",
      "sentence_en": "The ham is salty.",
      "audio_url_male": null,
      "difficulty": "initiation",
      "category": "food",
      "created_at": "2025-11-20T13:35:00.000Z",
      "updated_at": "2025-11-20T13:35:00.000Z"
    },
    {
      "id": "",
      "sentence_zh": "香肠很香。",
      "sentence_pinyin": "Xiāngcháng hěn xiāng.",
      "sentence_fr": "La saucisse sent bon.",
      "sentence_en": "The sausage smells good.",
      "audio_url_male": null,
      "difficulty": "initiation",
      "category": "food",
      "created_at": "2025-11-20T13:35:00.000Z",
      "updated_at": "2025-11-20T13:35:00.000Z"
    },
    {
      "id": "",
      "sentence_zh": "培根很脆。",
      "sentence_pinyin": "Péigēn hěn cuì.",
      "sentence_fr": "Le bacon est croustillant.",
      "sentence_en": "The bacon is crispy.",
      "audio_url_male": null,
      "difficulty": "initiation",
      "category": "food",
      "created_at": "2025-11-20T13:35:00.000Z",
      "updated_at": "2025-11-20T13:35:00.000Z"
    },
    {
      "id": "",
      "sentence_zh": "酱油很咸。",
      "sentence_pinyin": "Jiàngyóu hěn xián.",
      "sentence_fr": "La sauce soja est salée.",
      "sentence_en": "Soy sauce is salty.",
      "audio_url_male": null,
      "difficulty": "initiation",
      "category": "food",
      "created_at": "2025-11-20T13:35:00.000Z",
      "updated_at": "2025-11-20T13:35:00.000Z"
    },
    {
      "id": "",
      "sentence_zh": "醋很酸。",
      "sentence_pinyin": "Cù hěn suān.",
      "sentence_fr": "Le vinaigre est acide.",
      "sentence_en": "Vinegar is sour.",
      "audio_url_male": null,
      "difficulty": "initiation",
      "category": "food",
      "created_at": "2025-11-20T13:35:00.000Z",
      "updated_at": "2025-11-20T13:35:00.000Z"
    },
    {
      "id": "",
      "sentence_zh": "油很滑。",
      "sentence_pinyin": "Yóu hěn huá.",
      "sentence_fr": "L'huile est glissante.",
      "sentence_en": "The oil is slippery.",
      "audio_url_male": null,
      "difficulty": "initiation",
      "category": "food",
      "created_at": "2025-11-20T13:35:00.000Z",
      "updated_at": "2025-11-20T13:35:00.000Z"
    },
    {
      "id": "",
      "sentence_zh": "芝麻很香。",
      "sentence_pinyin": "Zhīma hěn xiāng.",
      "sentence_fr": "Le sésame sent bon.",
      "sentence_en": "Sesame smells good.",
      "audio_url_male": null,
      "difficulty": "initiation",
      "category": "food",
      "created_at": "2025-11-20T13:35:00.000Z",
      "updated_at": "2025-11-20T13:35:00.000Z"
    },
    {
      "id": "",
      "sentence_zh": "花椒很麻。",
      "sentence_pinyin": "Huājiāo hěn má.",
      "sentence_fr": "Le poivre de Sichuan est piquant.",
      "sentence_en": "Sichuan pepper is numbing.",
      "audio_url_male": null,
      "difficulty": "initiation",
      "category": "food",
      "created_at": "2025-11-20T13:35:00.000Z",
      "updated_at": "2025-11-20T13:35:00.000Z"
    },
    {
      "id": "",
      "sentence_zh": "姜很辣。",
      "sentence_pinyin": "Jiāng hěn là.",
      "sentence_fr": "Le gingembre est piquant.",
      "sentence_en": "Ginger is spicy.",
      "audio_url_male": null,
      "difficulty": "initiation",
      "category": "food",
      "created_at": "2025-11-20T13:35:00.000Z",
      "updated_at": "2025-11-20T13:35:00.000Z"
    },
    {
      "id": "",
      "sentence_zh": "葱很香。",
      "sentence_pinyin": "Cōng hěn xiāng.",
      "sentence_fr": "L'oignon vert sent bon.",
      "sentence_en": "The green onion smells good.",
      "audio_url_male": null,
      "difficulty": "initiation",
      "category": "food",
      "created_at": "2025-11-20T13:35:00.000Z",
      "updated_at": "2025-11-20T13:35:00.000Z"
    },
    {
      "id": "",
      "sentence_zh": "香菜很香。",
      "sentence_pinyin": "Xiāngcài hěn xiāng.",
      "sentence_fr": "La coriandre sent bon.",
      "sentence_en": "Cilantro smells good.",
      "audio_url_male": null,
      "difficulty": "initiation",
      "category": "food",
      "created_at": "2025-11-20T13:35:00.000Z",
      "updated_at": "2025-11-20T13:35:00.000Z"
    }
  ]
}
